Metadata-Version: 2.1
Name: Marius-firstpackage
Version: 0.2.0
Summary: This is my first package
Home-page: UNKNOWN
Author: Marius Mihai Neagu
Author-email: marius.neagu828@gmail.com
License: UNKNOWN
Platform: UNKNOWN
